README.md
setup.py
tf_cop/__init__.py
tf_cop/api.py
tf_cop/checker.py
tf_cop/cli.py
tf_cop/resource_result.py
tf_cop.egg-info/PKG-INFO
tf_cop.egg-info/SOURCES.txt
tf_cop.egg-info/dependency_links.txt
tf_cop.egg-info/entry_points.txt
tf_cop.egg-info/requires.txt
tf_cop.egg-info/top_level.txt
tf_cop/_default_review_book/data/s3.yaml
tf_cop/_default_review_book/resource/acm.yaml
tf_cop/_default_review_book/resource/api.yaml
tf_cop/_default_review_book/resource/batch.yaml
tf_cop/_default_review_book/resource/db.yaml
tf_cop/_default_review_book/resource/dynamodb.yaml
tf_cop/_default_review_book/resource/elasticache.yaml
tf_cop/_default_review_book/resource/elb.yaml
tf_cop/_default_review_book/resource/iam.yaml
tf_cop/_default_review_book/resource/instance.yaml
tf_cop/_default_review_book/resource/kms.yaml
tf_cop/_default_review_book/resource/lambda.yaml
tf_cop/_default_review_book/resource/rds.yaml
tf_cop/_default_review_book/resource/s3.yaml
tf_cop/_default_review_book/resource/sample_s3.yaml
tf_cop/_default_review_book/resource/sqs.yaml