Metadata-Version: 2.1
Name: tf-cop
Version: 0.2.0
Summary: auto terraform review
Home-page: https://github.com/ys-tydy/tf_cop
Author: ys-tydy
Author-email: 
License: ys-tydy
Keywords: terraform hcl review
Platform: UNKNOWN
Classifier: Development Status :: 3 - Alpha
Classifier: Programming Language :: Python :: 3.6
